pypi_oldest_requirements/__init__.py
pypi_oldest_requirements/_version.py
pypi_oldest_requirements/cli.py
pypi_oldest_requirements/misc.py
pypi_oldest_requirements/pypi.py
pypi_oldest_requirements/req_parse.py
pypi_oldest_requirements/req_write.py
pypi_oldest_requirements-2022.1.0.dist-info/AUTHORS.rst
pypi_oldest_requirements-2022.1.0.dist-info/LICENSE
pypi_oldest_requirements-2022.1.0.dist-info/METADATA
pypi_oldest_requirements-2022.1.0.dist-info/WHEEL
pypi_oldest_requirements-2022.1.0.dist-info/entry_points.txt
pypi_oldest_requirements-2022.1.0.dist-info/top_level.txt
pypi_oldest_requirements-2022.1.0.dist-info/RECORD
