Metadata-Version: 2.1
Name: pypi-oldest-requirements
Version: 2022.1.0
Summary: Get "oldest" fitting requirements from pypi
Home-page: https://github.com/renefritze/pypi_oldest_requirements
Author: René Fritze
Author-email: rene.fritze@wwu.de
License: BSD license
Keywords: pypi_oldest_requirements
Classifier: Development Status :: 4 - Beta
Classifier: Intended Audience :: Developers
Classifier: License :: OSI Approved :: BSD License
Classifier: Natural Language :: English
Classifier: Programming Language :: Python :: 3.10
Classifier: Programming Language :: Python :: 3.8
Classifier: Programming Language :: Python :: 3.9
Requires-Python: >=3.6
License-File: LICENSE
License-File: AUTHORS.rst
Requires-Dist: packaging
Requires-Dist: requirements-parser
Requires-Dist: requests
Requires-Dist: requests-toolbelt
Requires-Dist: typer
Requires-Dist: click (<8)
